unasync_cli/__init__.py
unasync_cli/__main__.py
unasync_cli/main.py
unasync_cli-0.0.9.dist-info/entry_points.txt
unasync_cli-0.0.9.dist-info/LICENSE
unasync_cli-0.0.9.dist-info/WHEEL
unasync_cli-0.0.9.dist-info/METADATA
unasync_cli-0.0.9.dist-info/RECORD
