Metadata-Version: 2.1
Name: unasync-cli
Version: 0.0.9
Summary: Command line interface for unasync
Home-page: https://github.com/leynier/unasync-cli
License: MIT
Author: Leynier Gutiérrez González
Author-email: leynier41@gmail.com
Requires-Python: >=3.6.14,<4.0.0
Classifier: License :: OSI Approved :: MIT License
Classifier: Programming Language :: Python :: 3
Classifier: Programming Language :: Python :: 3.10
Classifier: Programming Language :: Python :: 3.7
Classifier: Programming Language :: Python :: 3.8
Classifier: Programming Language :: Python :: 3.9
Requires-Dist: setuptools (>=58.2.0,<59.0.0)
Requires-Dist: typer (>=0.4.0,<0.5.0)
Requires-Dist: unasync (>=0.5.0,<0.6.0)
Project-URL: Documentation, https://github.com/leynier/unasync-cli
Project-URL: Repository, https://github.com/leynier/unasync-cli
